cs/rfc2616.py
cs_rfc2616-20250306.dist-info/WHEEL
cs_rfc2616-20250306.dist-info/METADATA
cs_rfc2616-20250306.dist-info/RECORD
